moat/micro/__init__.py
moat/micro/_cfg.yaml
moat/micro/_main.py
moat/micro/_rtc.py
moat/micro/_test.py
moat/micro/alert.py
moat/micro/direct.py
moat/micro/files.py
moat/micro/fuse.py
moat/micro/os_error_list.py
moat/micro/romfs.py
moat/micro/rtc.py
moat/micro/setup.py
moat/micro/util.py
moat/micro/_embed/_tag.py
moat/micro/_embed/boot.py
moat/micro/_embed/main.py
moat/micro/_embed/main_unix.py
moat/micro/_embed/manifest.py
moat/micro/_embed/OFF/cmd.py
moat/micro/_embed/OFF/rpy1.py
moat/micro/_embed/OFF/std.py
moat/micro/_embed/boards/esp32/c6_gaggenau/main.py
moat/micro/_embed/boards/unix/test/manifest.py
moat/micro/_embed/lib/async_queue.py
moat/micro/_embed/lib/manifest.py
moat/micro/_embed/lib/mpdb.py
moat/micro/_embed/lib/rtc.py
moat/micro/_embed/lib/serialpacker.py
moat/micro/_embed/lib/app/__init__.py
moat/micro/_embed/lib/app/_sys.py
moat/micro/_embed/lib/app/_sys_.py
moat/micro/_embed/lib/app/_test.py
moat/micro/_embed/lib/app/cfg.py
moat/micro/_embed/lib/app/fs.py
moat/micro/_embed/lib/app/i2c.py
moat/micro/_embed/lib/app/link.py
moat/micro/_embed/lib/app/part.py
moat/micro/_embed/lib/app/ping.py
moat/micro/_embed/lib/app/port.py
moat/micro/_embed/lib/app/remote.py
moat/micro/_embed/lib/app/romfs.py
moat/micro/_embed/lib/app/rtc.py
moat/micro/_embed/lib/app/serial.py
moat/micro/_embed/lib/app/stdio.py
moat/micro/_embed/lib/app/sub.py
moat/micro/_embed/lib/app/wdt.py
moat/micro/_embed/lib/app/net/__init__.py
moat/micro/_embed/lib/app/net/tcp.py
moat/micro/_embed/lib/moat/__init__.py
moat/micro/_embed/lib/moat/go_.py
moat/micro/_embed/lib/moat/ems/battery/__init__.py
moat/micro/_embed/lib/moat/ems/battery/_base.py
moat/micro/_embed/lib/moat/lib/__init__.py
moat/micro/_embed/lib/moat/lib/_proxy.py
moat/micro/_embed/lib/moat/lib/proxy.py
moat/micro/_embed/lib/moat/lib/codec/__init__.py
moat/micro/_embed/lib/moat/lib/codec/_base.py
moat/micro/_embed/lib/moat/lib/codec/cbor.py
moat/micro/_embed/lib/moat/lib/codec/errors.py
moat_micro-0.18.1.dist-info/licenses/LICENSE.txt
moat_micro-0.18.1.dist-info/METADATA
moat_micro-0.18.1.dist-info/WHEEL
moat_micro-0.18.1.dist-info/top_level.txt
moat_micro-0.18.1.dist-info/RECORD
