Metadata-Version: 2.4
Name: moat-micro
Version: 0.18.1
Summary: REPLACE ME
Author-email: Matthias Urlichs <matthias@urlichs.de>
Project-URL: homepage, https://m-o-a-t.org
Project-URL: repository, https://github.com/M-o-a-T/moat
Keywords: MoaT
Classifier: Development Status :: 4 - Beta
Classifier: Framework :: AnyIO
Classifier: Framework :: Trio
Classifier: Framework :: AsyncIO
Classifier: Programming Language :: Python :: 3
Classifier: Intended Audience :: Developers
Requires-Python: >=3.8
License-File: LICENSE.txt
Requires-Dist: anyio~=4.2
Requires-Dist: msgpack
Requires-Dist: serialpacker>=0.10.3
Requires-Dist: pyfuse3>=3.2
Requires-Dist: moat-util~=0.62.2
Requires-Dist: moat-src~=0.10.6
Requires-Dist: asyncdbus
Requires-Dist: smbus3
Requires-Dist: moat-lib-rpc~=0.5.1
Requires-Dist: moat-lib-codec~=0.4.10
Requires-Dist: moat-lib-config~=0.1.1
Requires-Dist: moat-lib-micro~=0.2.1
Requires-Dist: moat-lib-pid~=0.6.7
Requires-Dist: moat-lib-proxy~=0.1.0
Requires-Dist: moat-lib-ring~=0.2.2
Requires-Dist: moat-lib-run~=0.1.1
Requires-Dist: moat-lib-stream~=0.1.3
Dynamic: license-file
